s2and/__init__.py
s2and/consts.py
s2and/data.py
s2and/eval.py
s2and/feature_port.py
s2and/featurizer.py
s2and/file_cache.py
s2and/model.py
s2and/mp.py
s2and/plotting_utils.py
s2and/sampling.py
s2and/shap_utils.py
s2and/subblocking.py
s2and/text.py
s2and-0.30.0.dist-info/licenses/LICENSE
s2and_rust/s2and_rust/__init__.py
s2and-0.30.0.dist-info/METADATA
s2and-0.30.0.dist-info/WHEEL
s2and-0.30.0.dist-info/top_level.txt
s2and-0.30.0.dist-info/RECORD
