Metadata-Version: 2.4
Name: s2and
Version: 0.30.0
Summary: S2AND
Author: Sergey Feldman, Daniel King, Shivashankar Subramanian
License: MIT
Requires-Python: <3.12,>=3.11
License-File: LICENSE
Requires-Dist: awscli
Requires-Dist: fasttext-wheel>=0.9.2
Requires-Dist: pycld2>=0.41
Requires-Dist: scikit-learn==1.7.1
Requires-Dist: text-unidecode==1.3
Requires-Dist: requests<3,>=2.28
Requires-Dist: urllib3>=2.6.3
Requires-Dist: hyperopt==0.2.7
Requires-Dist: pandas<2.2,>=1.5
Requires-Dist: lightgbm==4.6.0
Requires-Dist: fastcluster<2,>=1.2.6
Requires-Dist: genieclust<2,>=1.1.4
Requires-Dist: matplotlib<3.9,>=3.7
Requires-Dist: fonttools>=4.60.2
Requires-Dist: seaborn<0.14,>=0.12
Requires-Dist: tqdm<5,>=4.64
Requires-Dist: strsimpy<0.3,>=0.2
Requires-Dist: jellyfish<2,>=0.9
Requires-Dist: numpy<2,>=1.24
Requires-Dist: orjson<4,>=3.9
Requires-Dist: pyasn1>=0.6.2
Requires-Dist: shap
Requires-Dist: sinonym>=0.2.2
Requires-Dist: importlib-metadata>=4.13; python_version < "3.10"
Provides-Extra: dev
Requires-Dist: pytest==8.4.1; extra == "dev"
Requires-Dist: pytest-cov<6,>=4; extra == "dev"
Requires-Dist: mypy>=1.5.1; extra == "dev"
Requires-Dist: black==24.8.0; extra == "dev"
Requires-Dist: flake8<8,>=6; extra == "dev"
Requires-Dist: ruff<0.7,>=0.4; extra == "dev"
Requires-Dist: click<9,>=8; extra == "dev"
Requires-Dist: ipykernel; extra == "dev"
Provides-Extra: rust
Requires-Dist: s2and-rust>=0.30.0; extra == "rust"
Dynamic: license-file
